{"cameraMode":{"drawMode":0,"name":"Shaded","section":"Shading Mode"},"sceneLighting":true,"audioPlay":false,"sceneViewState":{"m_AlwaysRefresh":false,"showFog":true,"showSkybox":true,"showFlares":true,"showImageEffects":true,"showParticleSystems":true,"showVisualEffectGraphs":true,"m_FxEnabled":true},"in2DMode":false,"pivot":{"x":-42.483978271484378,"y":-2.780412197113037,"z":56.07313537597656},"rotation":{"x":-0.16080789268016816,"y":0.38743865489959719,"z":-0.06882278621196747,"w":-0.905217707157135},"size":14.537348747253418,"orthographic":false}